datalog/__init__.py
datalog/data.py
datalog/device.py
datalog/rest.py
datalog/adc/__init__.py
datalog/adc/adc.conf.dist
datalog/adc/adc.py
datalog/adc/config.py
datalog/adc/fetch.py
datalog/adc/hrdl/__init__.py
datalog/adc/hrdl/constants.py
datalog/adc/hrdl/picolog.py
datalog-0.7.8.dist-info/METADATA
datalog-0.7.8.dist-info/RECORD
datalog-0.7.8.dist-info/WHEEL
datalog-0.7.8.dist-info/top_level.txt
