Metadata-Version: 2.1
Name: datalog
Version: 0.7.8
Summary: Python library to interface with PicoLog ADC hardware
Home-page: https://github.com/SeanDS/datalog
Author: Sean Leavey
Author-email: datalog@attackllama.com
License: GPLv3
Platform: UNKNOWN
Classifier: Intended Audience :: Science/Research
Classifier: License :: OSI Approved :: GNU General Public License v3 (GPLv3)
Classifier: Natural Language :: English
Classifier: Programming Language :: Python :: 3
Classifier: Programming Language :: Python :: 3.5
Requires-Dist: appdirs
